aibox/Tokenize.py
aibox/__init__.py
aibox-0.0.3.dist-info/METADATA
aibox-0.0.3.dist-info/WHEEL
aibox-0.0.3.dist-info/top_level.txt
aibox-0.0.3.dist-info/RECORD
